deskew/__init__.py
deskew/deskewer.py
paper_deskew-0.1.9.dist-info/METADATA
paper_deskew-0.1.9.dist-info/WHEEL
paper_deskew-0.1.9.dist-info/top_level.txt
paper_deskew-0.1.9.dist-info/RECORD
