Metadata-Version: 2.1
Name: paper-deskew
Version: 0.1.9
Summary: deskew
Home-page: https://github.com/pbcquoc/deskew
Author: pbcquoc
Author-email: pbcquoc@gmail.com
License: UNKNOWN
Platform: UNKNOWN
Classifier: Programming Language :: Python :: 3
Classifier: License :: OSI Approved :: MIT License
Classifier: Operating System :: OS Independent
Requires-Python: >=3.6
Requires-Dist: fast-histogram (==0.9)
